actinia_satellite_plugin/__init__.py
actinia_satellite_plugin/aws_sentinel2a_query.py
actinia_satellite_plugin/endpoints.py
actinia_satellite_plugin/ephemeral_landsat_ndvi_processor.py
actinia_satellite_plugin/ephemeral_sentinel2_ndvi_processor.py
actinia_satellite_plugin/persistent_landsat_timeseries_creator.py
actinia_satellite_plugin/persistent_sentinel2_timeseries_creator.py
actinia_satellite_plugin/satellite_query.py
actinia_satellite_plugin-0.3.0.dist-info/licenses/AUTHORS.rst
actinia_satellite_plugin-0.3.0.dist-info/licenses/LICENSE.txt
actinia_satellite_plugin-0.3.0.dist-info/METADATA
actinia_satellite_plugin-0.3.0.dist-info/WHEEL
actinia_satellite_plugin-0.3.0.dist-info/top_level.txt
actinia_satellite_plugin-0.3.0.dist-info/RECORD
