Metadata-Version: 2.4
Name: actinia-satellite-plugin
Version: 0.3.0
Summary: An actinia-core plugin which adds efficient satellite data handling to actinia-core
Author: Soeren Gebbert, Carmen Tawalika, Markus Neteler, Lina Krisztian
Project-URL: Homepage, https://github.com/mundialis/actinia-satellite-plugin
Project-URL: Tutorial, https://mundialis.github.io/actinia_core
Project-URL: API_Docs, https://redocly.github.io/redoc/?url=https://actinia.mundialis.de/latest/swagger.json
Keywords: processing,earth observation,cloud-based processing,rest api,gis,grass gis,osgeo,satellite
Classifier: License :: OSI Approved :: GNU General Public License v3 or later (GPLv3+)
Classifier: Programming Language :: Python :: 3
Requires-Python: >=3.8
License-File: LICENSE.txt
License-File: AUTHORS.rst
Provides-Extra: test
Requires-Dist: pytest; extra == "test"
Requires-Dist: pytest-cov; extra == "test"
Dynamic: license-file
